{
  "Collections": [
    {
      "name": "abstract",
      "preview_url": "https://raw.githubusercontent.com/edwinmacalopu/wxllpaper/master/liq_12_pre.png",
      "preview_thumbnail_url": "https://raw.githubusercontent.com/edwinmacalopu/wxllpaper/master/liq_12_pre.png"
    },
    {
      "name": "isometric3D",
      "preview_url": "https://raw.githubusercontent.com/edwinmacalopu/wxllpaper/master/3d01.png",
      "preview_thumbnail_url": "https://raw.githubusercontent.com/edwinmacalopu/wxllpaper/master/3d01.png"
    },
    {
      "name": "memphis",
      "preview_url": "https://github.com/jahirfiquitiva/Website-Resources/raw/master/wallpapers/unsplash_c.png",
      "preview_thumbnail_url": "https://github.com/jahirfiquitiva/Website-Resources/raw/master/wallpapers/thumbnails/unsplash_c.png"
    },
    {
      "name": "architecture",
      "preview_url": "https://raw.githubusercontent.com/edwinmacalopu/wxllpaper/master/GORR.png",
      "preview_thumbnail_url": "https://raw.githubusercontent.com/edwinmacalopu/wxllpaper/master/GORR.png"
    },
    {
      "name": "earth",
      "preview_url": "https://github.com/jahirfiquitiva/Website-Resources/raw/master/wallpapers/unsplash_d.png",
      "preview_thumbnail_url": "https://github.com/jahirfiquitiva/Website-Resources/raw/master/wallpapers/thumbnails/unsplash_d.png"
    }
  ],
  "Wallpapers": [
    {
       "name": "isometric blue",
      "author": "miluwalls",
      "url": "https://raw.githubusercontent.com/edwinmacalopu/wxllpaper/master/3d03.png",
      "thumbnail": "https://raw.githubusercontent.com/edwinmacalopu/wxllpaper/master/3d03.png",
      "dimensions": "1440 x 2560",
      "copyright": "Free (do whatever you want)",
      "collections": "featured,isometric3D"
    },
    {
       "name": "isometric green",
      "author": "miluwalls",
      "url": "https://raw.githubusercontent.com/edwinmacalopu/wxllpaper/master/3d02.png",
      "thumbnail": "https://raw.githubusercontent.com/edwinmacalopu/wxllpaper/master/3d02.png",
      "dimensions": "1440 x 2560",
      "copyright": "Free (do whatever you want)",
      "collections": "featured,isometric3D"
    },
    {
       "name": "isometric purple",
      "author": "miluwalls",
      "url": "https://raw.githubusercontent.com/edwinmacalopu/wxllpaper/master/3d01.png",
      "thumbnail": "https://raw.githubusercontent.com/edwinmacalopu/wxllpaper/master/3d01.png",
      "dimensions": "1440 x 2560",
      "copyright": "Free (do whatever you want)",
      "collections": "featured,isometric3D"
    },
     {
       "name": "mountain",
      "author": "miluwalls",
      "url": "https://raw.githubusercontent.com/edwinmacalopu/wxllpaper/master/mountn4.png",
      "thumbnail": "https://raw.githubusercontent.com/edwinmacalopu/wxllpaper/master/mountn4.png",
      "dimensions": "1440 x 2560",
      "copyright": "Free (do whatever you want)",
      "collections": "featured,abstract"
    },
     {
       "name": "mountain",
      "author": "miluwalls",
      "url": "https://raw.githubusercontent.com/edwinmacalopu/wxllpaper/master/mountn3.png",
      "thumbnail": "https://raw.githubusercontent.com/edwinmacalopu/wxllpaper/master/mountn3.png",
      "dimensions": "1440 x 2560",
      "copyright": "Free (do whatever you want)",
      "collections": "featured,abstract"
    },
     {
       "name": "mountain",
      "author": "miluwalls",
      "url": "https://raw.githubusercontent.com/edwinmacalopu/wxllpaper/master/mountn2.png",
      "thumbnail": "https://raw.githubusercontent.com/edwinmacalopu/wxllpaper/master/mountn2.png",
      "dimensions": "1440 x 2560",
      "copyright": "Free (do whatever you want)",
      "collections": "featured,abstract"
    },
    {
       "name": "mountain",
      "author": "miluwalls",
      "url": "https://raw.githubusercontent.com/edwinmacalopu/wxllpaper/master/mountn1.png",
      "thumbnail": "https://raw.githubusercontent.com/edwinmacalopu/wxllpaper/master/mountn1.png",
      "dimensions": "1440 x 2560",
      "copyright": "Free (do whatever you want)",
      "collections": "featured,abstract"
    },
    {
       "name": "camel dark",
      "author": "miluwalls",
      "url": "https://raw.githubusercontent.com/edwinmacalopu/wxllpaper/master/camel_dark.png",
      "thumbnail": "https://raw.githubusercontent.com/edwinmacalopu/wxllpaper/master/camel_dark.png",
      "dimensions": "1440 x 2560",
      "copyright": "Free (do whatever you want)",
      "collections": "featured,abstract"
    },
    {
       "name": "camel",
      "author": "miluwalls",
      "url": "https://raw.githubusercontent.com/edwinmacalopu/wxllpaper/master/camel.png",
      "thumbnail": "https://raw.githubusercontent.com/edwinmacalopu/wxllpaper/master/camel.png",
      "dimensions": "1440 x 2560",
      "copyright": "Free (do whatever you want)",
      "collections": "featured,abstract"
    },
    {
       "name": "insectfirefly green",
      "author": "miluwalls",
      "url": "https://raw.githubusercontent.com/edwinmacalopu/wxllpaper/master/insectfirefly_green.png",
      "thumbnail": "https://raw.githubusercontent.com/edwinmacalopu/wxllpaper/master/insectfirefly_green.png",
      "dimensions": "1440 x 2560",
      "copyright": "Free (do whatever you want)",
      "collections": "featured,abstract"
    },
    {
       "name": "insectfirefly",
      "author": "miluwalls",
      "url": "https://raw.githubusercontent.com/edwinmacalopu/wxllpaper/master/insectfirefly.png",
      "thumbnail": "https://raw.githubusercontent.com/edwinmacalopu/wxllpaper/master/insectfirefly.png",
      "dimensions": "1440 x 2560",
      "copyright": "Free (do whatever you want)",
      "collections": "featured,abstract"
    },
    {
       "name": "Dolphin",
      "author": "miluwalls",
      "url": "https://raw.githubusercontent.com/edwinmacalopu/wxllpaper/master/delfin_edwin.png",
      "thumbnail": "https://raw.githubusercontent.com/edwinmacalopu/wxllpaper/master/delfin_edwin.png",
      "dimensions": "1440 x 2560",
      "copyright": "Free (do whatever you want)",
      "collections": "featured,abstract"
    },
    {
       "name": "owl",
      "author": "miluwalls",
      "url": "https://raw.githubusercontent.com/edwinmacalopu/wxllpaper/master/buho_edwin.png",
      "thumbnail": "https://raw.githubusercontent.com/edwinmacalopu/wxllpaper/master/buho_edwin.png",
      "dimensions": "1440 x 2560",
      "copyright": "Free (do whatever you want)",
      "collections": "featured,abstract"
    },
     {
       "name": "deersi",
      "author": "miluwalls",
      "url": "https://raw.githubusercontent.com/edwinmacalopu/wxllpaper/master/deer_edwin.png",
      "thumbnail": "https://raw.githubusercontent.com/edwinmacalopu/wxllpaper/master/deer_edwin.png",
      "dimensions": "1440 x 2560",
      "copyright": "Free (do whatever you want)",
      "collections": "featured,abstract"
    },
    {
       "name": "foxi",
      "author": "miluwalls",
      "url": "https://raw.githubusercontent.com/edwinmacalopu/wxllpaper/master/fox_edwin.png",
      "thumbnail": "https://raw.githubusercontent.com/edwinmacalopu/wxllpaper/master/fox_edwin.png",
      "dimensions": "1440 x 2560",
      "copyright": "Free (do whatever you want)",
      "collections": "featured,abstract"
    },
    {
       "name": "jungle green",
      "author": "miluwalls",
      "url": "https://raw.githubusercontent.com/edwinmacalopu/wxllpaper/master/edwin_02.png",
      "thumbnail": "https://raw.githubusercontent.com/edwinmacalopu/wxllpaper/master/edwin_02.png",
      "dimensions": "1440 x 2560",
      "copyright": "Free (do whatever you want)",
      "collections": "featured,abstract"
    },
    {
       "name": "jungle red",
      "author": "miluwalls",
      "url": "https://raw.githubusercontent.com/edwinmacalopu/wxllpaper/master/edwin_01.png",
      "thumbnail": "https://raw.githubusercontent.com/edwinmacalopu/wxllpaper/master/edwin_01.png",
      "dimensions": "1440 x 2560",
      "copyright": "Free (do whatever you want)",
      "collections": "featured,abstract"
    },
    {
       "name": "AltosAdventure2",
      "author": "Mathy Eckerdt",
      "url": "https://raw.githubusercontent.com/edwinmacalopu/wxllpaper/master/AltosAdventure2.png",
      "thumbnail": "https://raw.githubusercontent.com/edwinmacalopu/wxllpaper/master/AltosAdventure2.png",
      "dimensions": "1440 x 2560",
      "copyright": "Free (do whatever you want)",
      "collections": "featured,abstract"
    },
    {
       "name": "AltosAdventure1",
      "author": "Mathy Eckerdt",
      "url": "https://raw.githubusercontent.com/edwinmacalopu/wxllpaper/master/AltosAdventure1.png",
      "thumbnail": "https://raw.githubusercontent.com/edwinmacalopu/wxllpaper/master/AltosAdventure1.png",
      "dimensions": "1440 x 2560",
      "copyright": "Free (do whatever you want)",
      "collections": "featured,abstract"
    },
    {
       "name": "AnotherPlanet2",
      "author": "Mathy Eckerdt",
      "url": "https://raw.githubusercontent.com/edwinmacalopu/wxllpaper/master/AnotherPlanet2.png",
      "thumbnail": "https://raw.githubusercontent.com/edwinmacalopu/wxllpaper/master/AnotherPlanet2.png",
      "dimensions": "1440 x 2560",
      "copyright": "Free (do whatever you want)",
      "collections": "featured,abstract"
    },
    {
       "name": "AnotherPlanet1",
      "author": "Mathy Eckerdt",
      "url": "https://raw.githubusercontent.com/edwinmacalopu/wxllpaper/master/AnotherPlanet1.png",
      "thumbnail": "https://raw.githubusercontent.com/edwinmacalopu/wxllpaper/master/AnotherPlanet1.png",
      "dimensions": "1440 x 2560",
      "copyright": "Free (do whatever you want)",
      "collections": "featured,abstract"
    },
    {
       "name": "FireInTheForest2",
      "author": "Mathy Eckerdt",
      "url": "https://raw.githubusercontent.com/edwinmacalopu/wxllpaper/master/FireInTheForest2.png",
      "thumbnail": "https://raw.githubusercontent.com/edwinmacalopu/wxllpaper/master/FireInTheForest2.png",
      "dimensions": "1440 x 2560",
      "copyright": "Free (do whatever you want)",
      "collections": "featured,abstract"
    },
    {
       "name": "FireInTheForest1",
      "author": "Mathy Eckerdt",
      "url": "https://raw.githubusercontent.com/edwinmacalopu/wxllpaper/master/FireInTheForest1.png",
      "thumbnail": "https://raw.githubusercontent.com/edwinmacalopu/wxllpaper/master/FireInTheForest1.png",
      "dimensions": "1440 x 2560",
      "copyright": "Free (do whatever you want)",
      "collections": "featured,abstract"
    },
    {
       "name": "WhaleBlue1",
      "author": "Mathy Eckerdt",
      "url": "https://raw.githubusercontent.com/edwinmacalopu/wxllpaper/master/WhaleBlue1.png",
      "thumbnail": "https://raw.githubusercontent.com/edwinmacalopu/wxllpaper/master/WhaleBlue1.png",
      "dimensions": "1440 x 2560",
      "copyright": "Free (do whatever you want)",
      "collections": "featured,abstract"
    },
    {
       "name": "WhaleGreen1",
      "author": "Mathy Eckerdt",
      "url": "https://raw.githubusercontent.com/edwinmacalopu/wxllpaper/master/WhaleGreen1.png",
      "thumbnail": "https://raw.githubusercontent.com/edwinmacalopu/wxllpaper/master/WhaleGreen1.png",
      "dimensions": "1440 x 2560",
      "copyright": "Free (do whatever you want)",
      "collections": "featured,abstract"
    },
     {
       "name": "Wolf1",
      "author": "Mathy Eckerdt",
      "url": "https://raw.githubusercontent.com/edwinmacalopu/wxllpaper/master/Wolf1.png",
      "thumbnail": "https://raw.githubusercontent.com/edwinmacalopu/wxllpaper/master/Wolf1.png",
      "dimensions": "1440 x 2560",
      "copyright": "Free (do whatever you want)",
      "collections": "featured,abstract"
    },
    {
       "name": "Wolf",
      "author": "Mathy Eckerdt",
      "url": "https://raw.githubusercontent.com/edwinmacalopu/wxllpaper/master/Wolf.png",
      "thumbnail": "https://raw.githubusercontent.com/edwinmacalopu/wxllpaper/master/Wolf.png",
      "dimensions": "1440 x 2560",
      "copyright": "Free (do whatever you want)",
      "collections": "featured,abstract"
    },
    {
       "name": "NewDesert4",
      "author": "Mathy Eckerdt",
      "url": "https://raw.githubusercontent.com/edwinmacalopu/wxllpaper/master/NewDesert4.png",
      "thumbnail": "https://raw.githubusercontent.com/edwinmacalopu/wxllpaper/master/NewDesert4.png",
      "dimensions": "1440 x 2560",
      "copyright": "Free (do whatever you want)",
      "collections": "featured,abstract"
    },
    {
       "name": "NewDesert3",
      "author": "Mathy Eckerdt",
      "url": "https://raw.githubusercontent.com/edwinmacalopu/wxllpaper/master/NewDesert3.png",
      "thumbnail": "https://raw.githubusercontent.com/edwinmacalopu/wxllpaper/master/NewDesert3.png",
      "dimensions": "1440 x 2560",
      "copyright": "Free (do whatever you want)",
      "collections": "featured,abstract"
    },
   
    {
       "name": "FoxLandscape2",
      "author": "Mathy Eckerdt",
      "url": "https://raw.githubusercontent.com/edwinmacalopu/wxllpaper/master/FoxLandscape2.png",
      "thumbnail": "https://raw.githubusercontent.com/edwinmacalopu/wxllpaper/master/FoxLandscape2.png",
      "dimensions": "1440 x 2560",
      "copyright": "Free (do whatever you want)",
      "collections": "featured,abstract"
    },
    {
       "name": "FoxLandscape1",
      "author": "Mathy Eckerdt",
      "url": "https://raw.githubusercontent.com/edwinmacalopu/wxllpaper/master/FoxLandscape1.png",
      "thumbnail": "https://raw.githubusercontent.com/edwinmacalopu/wxllpaper/master/FoxLandscape1.png",
      "dimensions": "1440 x 2560",
      "copyright": "Free (do whatever you want)",
      "collections": "featured,abstract"
    },
    {
       "name": "BeautifulPlace2",
      "author": "Mathy Eckerdt",
      "url": "https://raw.githubusercontent.com/edwinmacalopu/wxllpaper/master/BeautifulPlace2.png",
      "thumbnail": "https://raw.githubusercontent.com/edwinmacalopu/wxllpaper/master/BeautifulPlace2.png",
      "dimensions": "1440 x 2560",
      "copyright": "Free (do whatever you want)",
      "collections": "featured,abstract"
    },
    {
       "name": "BeautifulPlace1",
      "author": "Mathy Eckerdt",
      "url": "https://raw.githubusercontent.com/edwinmacalopu/wxllpaper/master/BeautifulPlace1.png",
      "thumbnail": "https://raw.githubusercontent.com/edwinmacalopu/wxllpaper/master/BeautifulPlace1.png",
      "dimensions": "1440 x 2560",
      "copyright": "Free (do whatever you want)",
      "collections": "featured,abstract"
    },
    {
       "name": "BeautifulHouseRed",
      "author": "Mathy Eckerdt",
      "url": "https://raw.githubusercontent.com/edwinmacalopu/wxllpaper/master/BeautifulHouseRed.png",
      "thumbnail": "https://raw.githubusercontent.com/edwinmacalopu/wxllpaper/master/BeautifulHouseRed.png",
      "dimensions": "1440 x 2560",
      "copyright": "Free (do whatever you want)",
      "collections": "featured,abstract"
    },
    {
       "name": "AmoledGirl1",
      "author": "Mathy Eckerdt",
      "url": "https://raw.githubusercontent.com/edwinmacalopu/wxllpaper/master/AmoledGirl2.png",
      "thumbnail": "https://raw.githubusercontent.com/edwinmacalopu/wxllpaper/master/AmoledGirl2.png",
      "dimensions": "1440 x 2560",
      "copyright": "Free (do whatever you want)",
      "collections": "featured,abstract"
    },
    {
       "name": "AmoledGirl1",
      "author": "Mathy Eckerdt",
      "url": "https://raw.githubusercontent.com/edwinmacalopu/wxllpaper/master/AmoledGirl1.png",
      "thumbnail": "https://raw.githubusercontent.com/edwinmacalopu/wxllpaper/master/AmoledGirl1.png",
      "dimensions": "1440 x 2560",
      "copyright": "Free (do whatever you want)",
      "collections": "featured,abstract"
    },
    {
       "name": "iphone Xr",
      "author": "miluwalls",
      "url": "https://raw.githubusercontent.com/edwinmacalopu/wxllpaper/master/iphonexr3.png",
      "thumbnail": "https://raw.githubusercontent.com/edwinmacalopu/wxllpaper/master/iphonexr3.png",
      "dimensions": "1242 x 2208",
      "copyright": "Free (do whatever you want)",
      "collections": "featured,abstract"
    },
    {
       "name": "iphone Xr",
      "author": "miluwalls",
      "url": "https://raw.githubusercontent.com/edwinmacalopu/wxllpaper/master/iphonexr2.png",
      "thumbnail": "https://raw.githubusercontent.com/edwinmacalopu/wxllpaper/master/iphonexr2.png",
      "dimensions": "1242 x 2208",
      "copyright": "Free (do whatever you want)",
      "collections": "featured,abstract"
    },
    {
       "name": "iphone Xr",
      "author": "miluwalls",
      "url": "https://raw.githubusercontent.com/edwinmacalopu/wxllpaper/master/iphonexr1.png",
      "thumbnail": "https://raw.githubusercontent.com/edwinmacalopu/wxllpaper/master/iphonexr1.png",
      "dimensions": "1242 x 2208",
      "copyright": "Free (do whatever you want)",
      "collections": "featured,abstract"
    },
    {
       "name": "car",
      "author": "miluwalls",
      "url": "https://raw.githubusercontent.com/edwinmacalopu/wxllpaper/master/cars014.png",
      "thumbnail": "https://raw.githubusercontent.com/edwinmacalopu/wxllpaper/master/cars014.png",
      "dimensions": "2252 x 4002",
      "copyright": "Free (do whatever you want)",
      "collections": "featured,cars"
    },
    {
       "name": "car",
      "author": "miluwalls",
      "url": "https://raw.githubusercontent.com/edwinmacalopu/wxllpaper/master/cars013.png",
      "thumbnail": "https://raw.githubusercontent.com/edwinmacalopu/wxllpaper/master/cars013.png",
      "dimensions": "2252 x 4002",
      "copyright": "Free (do whatever you want)",
      "collections": "featured,cars"
    },
    {
       "name": "car",
      "author": "miluwalls",
      "url": "https://raw.githubusercontent.com/edwinmacalopu/wxllpaper/master/cars012.png",
      "thumbnail": "https://raw.githubusercontent.com/edwinmacalopu/wxllpaper/master/cars012.png",
      "dimensions": "2252 x 4002",
      "copyright": "Free (do whatever you want)",
      "collections": "featured,cars"
    },
    {
       "name": "car",
      "author": "miluwalls",
      "url": "https://raw.githubusercontent.com/edwinmacalopu/wxllpaper/master/cars011.png",
      "thumbnail": "https://raw.githubusercontent.com/edwinmacalopu/wxllpaper/master/cars011.png",
      "dimensions": "2252 x 4002",
      "copyright": "Free (do whatever you want)",
      "collections": "featured,cars"
    },
    {
       "name": "car",
      "author": "miluwalls",
      "url": "https://raw.githubusercontent.com/edwinmacalopu/wxllpaper/master/cars010.png",
      "thumbnail": "https://raw.githubusercontent.com/edwinmacalopu/wxllpaper/master/cars010.png",
      "dimensions": "2252 x 4002",
      "copyright": "Free (do whatever you want)",
      "collections": "featured,cars"
    },
    {
       "name": "car",
      "author": "miluwalls",
      "url": "https://raw.githubusercontent.com/edwinmacalopu/wxllpaper/master/cars09.png",
      "thumbnail": "https://raw.githubusercontent.com/edwinmacalopu/wxllpaper/master/cars09.png",
      "dimensions": "2252 x 4002",
      "copyright": "Free (do whatever you want)",
      "collections": "featured,cars"
    },    
    {
       "name": "car",
      "author": "miluwalls",
      "url": "https://raw.githubusercontent.com/edwinmacalopu/wxllpaper/master/cars06.png",
      "thumbnail": "https://raw.githubusercontent.com/edwinmacalopu/wxllpaper/master/cars06.png",
      "dimensions": "2252 x 4002",
      "copyright": "Free (do whatever you want)",
      "collections": "featured,cars"
    },
    {
       "name": "car",
      "author": "miluwalls",
      "url": "https://raw.githubusercontent.com/edwinmacalopu/wxllpaper/master/cars05.png",
      "thumbnail": "https://raw.githubusercontent.com/edwinmacalopu/wxllpaper/master/cars05.png",
      "dimensions": "2252 x 4002",
      "copyright": "Free (do whatever you want)",
      "collections": "featured,cars"
    },
    {
       "name": "car",
      "author": "miluwalls",
      "url": "https://raw.githubusercontent.com/edwinmacalopu/wxllpaper/master/cars04.png",
      "thumbnail": "https://raw.githubusercontent.com/edwinmacalopu/wxllpaper/master/cars04.png",
      "dimensions": "2252 x 4002",
      "copyright": "Free (do whatever you want)",
      "collections": "featured,cars"
    },
    {
       "name": "car",
      "author": "miluwalls",
      "url": "https://raw.githubusercontent.com/edwinmacalopu/wxllpaper/master/cars03.png",
      "thumbnail": "https://raw.githubusercontent.com/edwinmacalopu/wxllpaper/master/cars03.png",
      "dimensions": "2252 x 4002",
      "copyright": "Free (do whatever you want)",
      "collections": "featured,cars"
    },
    {
       "name": "car",
      "author": "miluwalls",
      "url": "https://raw.githubusercontent.com/edwinmacalopu/wxllpaper/master/cars01.png",
      "thumbnail": "https://raw.githubusercontent.com/edwinmacalopu/wxllpaper/master/cars01.png",
      "dimensions": "2252 x 4002",
      "copyright": "Free (do whatever you want)",
      "collections": "featured,cars"
    }, 
    {
       "name": "cubet green",
      "author": "miluwalls",
      "url": "https://raw.githubusercontent.com/edwinmacalopu/wxllpaper/master/cubet4.png",
      "thumbnail": "https://raw.githubusercontent.com/edwinmacalopu/wxllpaper/master/cubet4.png",
      "dimensions": "1500 x 2800",
      "copyright": "Free (do whatever you want)",
      "collections": "featured,abstract"
    }, 
     {
       "name": "cubet yellow",
      "author": "miluwalls",
      "url": "https://raw.githubusercontent.com/edwinmacalopu/wxllpaper/master/cubet3.png",
      "thumbnail": "https://raw.githubusercontent.com/edwinmacalopu/wxllpaper/master/cubet3.png",
      "dimensions": "1500 x 2800",
      "copyright": "Free (do whatever you want)",
      "collections": "featured,abstract"
    }, 
    {
       "name": "cubet red",
      "author": "miluwalls",
      "url": "https://raw.githubusercontent.com/edwinmacalopu/wxllpaper/master/cubet2.png",
      "thumbnail": "https://raw.githubusercontent.com/edwinmacalopu/wxllpaper/master/cubet2.png",
      "dimensions": "1500 x 2800",
      "copyright": "Free (do whatever you want)",
      "collections": "featured,abstract"
    }, 
    {
       "name": "cubet blue",
      "author": "miluwalls",
      "url": "https://raw.githubusercontent.com/edwinmacalopu/wxllpaper/master/cubet1.png",
      "thumbnail": "https://raw.githubusercontent.com/edwinmacalopu/wxllpaper/master/cubet1.png",
      "dimensions": "1500 x 2800",
      "copyright": "Free (do whatever you want)",
      "collections": "featured,abstract"
    },     
    {
       "name": "iphone Xs",
      "author": "google+",
      "url": "https://raw.githubusercontent.com/edwinmacalopu/wxllpaper/master/iphonered.png",
      "thumbnail": "https://raw.githubusercontent.com/edwinmacalopu/wxllpaper/master/iphonered.png",
      "dimensions": "4688 x 10150",
      "copyright": "Free (do whatever you want)",
      "collections": "featured,abstract"
    }, 
    {
       "name": "iphone Xs",
      "author": "google+",
      "url": "https://raw.githubusercontent.com/edwinmacalopu/wxllpaper/master/iphoneblue.png",
      "thumbnail": "https://raw.githubusercontent.com/edwinmacalopu/wxllpaper/master/iphoneblue.png",
      "dimensions": "4688 x 10150",
      "copyright": "Free (do whatever you want)",
      "collections": "featured,abstract"
    }, 
     {
       "name": "iphone Xs",
      "author": "google+",
      "url": "https://raw.githubusercontent.com/edwinmacalopu/wxllpaper/master/iphoneblack.png",
      "thumbnail": "https://raw.githubusercontent.com/edwinmacalopu/wxllpaper/master/iphoneblack.png",
      "dimensions": "4688 x 10150",
      "copyright": "Free (do whatever you want)",
      "collections": "featured,abstract"
    }, 
    {
       "name": "porsh2",
      "author": "google+",
      "url": "https://raw.githubusercontent.com/edwinmacalopu/wxllpaper/master/porsh2.png",
      "thumbnail": "https://raw.githubusercontent.com/edwinmacalopu/wxllpaper/master/porsh2.png",
      "dimensions": "2500 x 3840",
      "copyright": "Free (do whatever you want)",
      "collections": "featured,cars"
    }, 
    {
       "name": "porsh",
      "author": "google+",
      "url": "https://raw.githubusercontent.com/edwinmacalopu/wxllpaper/master/psrosh.png",
      "thumbnail": "https://raw.githubusercontent.com/edwinmacalopu/wxllpaper/master/psrosh.png",
      "dimensions": "2500 x 3840",
      "copyright": "Free (do whatever you want)",
      "collections": "featured,cars"
    }, 
    {
       "name": "rain",
      "author": "google+",
      "url": "https://raw.githubusercontent.com/edwinmacalopu/wxllpaper/master/pomq.png",
      "thumbnail": "https://raw.githubusercontent.com/edwinmacalopu/wxllpaper/master/pomq.png",
      "dimensions": "2500 x 3840",
      "copyright": "Free (do whatever you want)",
      "collections": "featured,abstract"
    }, 
    {
       "name": "mescla3",
      "author": "google+",
      "url": "https://raw.githubusercontent.com/edwinmacalopu/wxllpaper/master/mescla3.png",
      "thumbnail": "https://raw.githubusercontent.com/edwinmacalopu/wxllpaper/master/mescla3.png",
      "dimensions": "2500 x 3840",
      "copyright": "Free (do whatever you want)",
      "collections": "featured,abstract"
    }, 
     {
       "name": "mescla2",
      "author": "google+",
      "url": "https://raw.githubusercontent.com/edwinmacalopu/wxllpaper/master/mescla2.png",
      "thumbnail": "https://raw.githubusercontent.com/edwinmacalopu/wxllpaper/master/mescla2.png",
      "dimensions": "2500 x 3840",
      "copyright": "Free (do whatever you want)",
      "collections": "featured,abstract"
    }, 
    {
       "name": "mescla",
      "author": "google+",
      "url": "https://raw.githubusercontent.com/edwinmacalopu/wxllpaper/master/mescla1.png",
      "thumbnail": "https://raw.githubusercontent.com/edwinmacalopu/wxllpaper/master/mescla1.png",
      "dimensions": "2500 x 3840",
      "copyright": "Free (do whatever you want)",
      "collections": "featured,abstract"
    }, 
    {
       "name": "landascape blu",
      "author": "Imraan Virani",
      "url": "https://raw.githubusercontent.com/edwinmacalopu/wxllpaper/master/landscape%20blue-01.png",
      "thumbnail": "https://raw.githubusercontent.com/edwinmacalopu/wxllpaper/master/landscape%20blue-01.png",
      "dimensions": "3000 x 5333",
      "copyright": "Free (do whatever you want)",
      "collections": "featured,abstract"
    }, 
    {
       "name": "landascape",
      "author": "Imraan Virani",
      "url": "https://raw.githubusercontent.com/edwinmacalopu/wxllpaper/master/landscape-01.png",
      "thumbnail": "https://raw.githubusercontent.com/edwinmacalopu/wxllpaper/master/landscape-01.png",
      "dimensions": "3000 x 5333",
      "copyright": "Free (do whatever you want)",
      "collections": "featured,abstract"
    }, 
    {
       "name": "earth28",
      "author": "unsplash",
      "url": "https://raw.githubusercontent.com/edwinmacalopu/wxllpaper/master/lines.png",
      "thumbnail": "https://raw.githubusercontent.com/edwinmacalopu/wxllpaper/master/lines.png",
      "dimensions": "2500 x 3840",
      "copyright": "Free (do whatever you want)",
      "collections": "featured,earth"
    },
    {
       "name": "carblack",
      "author": "unsplash",
      "url": "https://raw.githubusercontent.com/edwinmacalopu/wxllpaper/master/carblack.png",
      "thumbnail": "https://raw.githubusercontent.com/edwinmacalopu/wxllpaper/master/carblack.png",
      "dimensions": "2500 x 3840",
      "copyright": "Free (do whatever you want)",
      "collections": "featured,cars"
    },
    {
       "name": "mercedes",
      "author": "miluwalls",
      "url": "https://raw.githubusercontent.com/edwinmacalopu/wxllpaper/master/merce.png",
      "thumbnail": "https://raw.githubusercontent.com/edwinmacalopu/wxllpaper/master/merce.png",
      "dimensions": "2500 x 3840",
      "copyright": "Free (do whatever you want)",
      "collections": "featured,cars"
    },
    {
       "name": "memphis10",
      "author": "miluwalls",
      "url": "https://raw.githubusercontent.com/edwinmacalopu/wxllpaper/master/artifi.png",
      "thumbnail": "https://raw.githubusercontent.com/edwinmacalopu/wxllpaper/master/artifi.png",
      "dimensions": "2500 x 3840",
      "copyright": "Free (do whatever you want)",
      "collections": "featured,memphis"
    },
     {
       "name": "cat 2",
      "author": "miluwalls",
      "url": "https://raw.githubusercontent.com/edwinmacalopu/wxllpaper/master/cat23.png",
      "thumbnail": "https://raw.githubusercontent.com/edwinmacalopu/wxllpaper/master/cat23.png",
      "dimensions": "2500 x 3840",
      "copyright": "Free (do whatever you want)",
      "collections": "featured,abstract"
    },
     {
       "name": "cat 1",
      "author": "miluwalls",
      "url": "https://raw.githubusercontent.com/edwinmacalopu/wxllpaper/master/cat22.png",
      "thumbnail": "https://raw.githubusercontent.com/edwinmacalopu/wxllpaper/master/cat22.png",
      "dimensions": "2500 x 3840",
      "copyright": "Free (do whatever you want)",
      "collections": "featured,abstract"
    },
    {
       "name": "asteroid yellow",
      "author": "miluwalls",
      "url": "https://raw.githubusercontent.com/edwinmacalopu/wxllpaper/master/asteroidyellow.png",
      "thumbnail": "https://raw.githubusercontent.com/edwinmacalopu/wxllpaper/master/asteroidyellow.png",
      "dimensions": "2500 x 3840",
      "copyright": "Free (do whatever you want)",
      "collections": "featured,abstract"
    },
     {
       "name": "asteroid green",
      "author": "miluwalls",
      "url": "https://raw.githubusercontent.com/edwinmacalopu/wxllpaper/master/asteroidgreen.png",
      "thumbnail": "https://raw.githubusercontent.com/edwinmacalopu/wxllpaper/master/asteroidgreen.png",
      "dimensions": "2500 x 3840",
      "copyright": "Free (do whatever you want)",
      "collections": "featured,abstract"
    },
     {
       "name": "asteroid red",
      "author": "miluwalls",
      "url": "https://raw.githubusercontent.com/edwinmacalopu/wxllpaper/master/asteroidred2.png",
      "thumbnail": "https://raw.githubusercontent.com/edwinmacalopu/wxllpaper/master/asteroidred2.png",
      "dimensions": "2500 x 3840",
      "copyright": "Free (do whatever you want)",
      "collections": "featured,abstract"
    },
     {
       "name": "asteroid blue",
      "author": "miluwalls",
      "url": "https://raw.githubusercontent.com/edwinmacalopu/wxllpaper/master/asteroidblue.png",
      "thumbnail": "https://raw.githubusercontent.com/edwinmacalopu/wxllpaper/master/asteroidblue.png",
      "dimensions": "2500 x 3840",
      "copyright": "Free (do whatever you want)",
      "collections": "featured,abstract"
    },
    {
       "name": "earth27",
      "author": "unsplash",
      "url": "https://raw.githubusercontent.com/edwinmacalopu/wxllpaper/master/volcan2.png",
      "thumbnail": "https://raw.githubusercontent.com/edwinmacalopu/wxllpaper/master/volcan2.png",
      "dimensions": "2500 x 3840",
      "copyright": "Free (do whatever you want)",
      "collections": "featured,earth"
    },
     {
       "name": "earth26",
      "author": "unsplash",
      "url": "https://raw.githubusercontent.com/edwinmacalopu/wxllpaper/master/volcan.png",
      "thumbnail": "https://raw.githubusercontent.com/edwinmacalopu/wxllpaper/master/volcan.png",
      "dimensions": "2500 x 3840",
      "copyright": "Free (do whatever you want)",
      "collections": "featured,earth"
    },
    {
       "name": "earth25",
      "author": "unsplash",
      "url": "https://raw.githubusercontent.com/edwinmacalopu/wxllpaper/master/asteroidred.png",
      "thumbnail": "https://raw.githubusercontent.com/edwinmacalopu/wxllpaper/master/asteroidred.png",
      "dimensions": "2500 x 3840",
      "copyright": "Free (do whatever you want)",
      "collections": "featured,earth"
    },
    {
       "name": "earth24",
      "author": "unsplash",
      "url": "https://raw.githubusercontent.com/edwinmacalopu/wxllpaper/master/planetorange.png",
      "thumbnail": "https://raw.githubusercontent.com/edwinmacalopu/wxllpaper/master/planetorange.png",
      "dimensions": "2500 x 3840",
      "copyright": "Free (do whatever you want)",
      "collections": "featured,earth"
    },
     {
       "name": "earth23",
      "author": "unsplash",
      "url": "https://raw.githubusercontent.com/edwinmacalopu/wxllpaper/master/planet1.png",
      "thumbnail": "https://raw.githubusercontent.com/edwinmacalopu/wxllpaper/master/planet1.png",
      "dimensions": "2500 x 3840",
      "copyright": "Free (do whatever you want)",
      "collections": "featured,earth"
    },
    {
       "name": "earth22",
      "author": "unsplash",
      "url": "https://raw.githubusercontent.com/edwinmacalopu/wxllpaper/master/solblack.png",
      "thumbnail": "https://raw.githubusercontent.com/edwinmacalopu/wxllpaper/master/solblack.png",
      "dimensions": "2500 x 3840",
      "copyright": "Free (do whatever you want)",
      "collections": "featured,earth"
    },
     {
       "name": "earth21",
      "author": "unsplash",
      "url": "https://raw.githubusercontent.com/edwinmacalopu/wxllpaper/master/wow21black.png",
      "thumbnail": "https://raw.githubusercontent.com/edwinmacalopu/wxllpaper/master/wow21black.png",
      "dimensions": "2500 x 3840",
      "copyright": "Free (do whatever you want)",
      "collections": "featured,earth"
    },
     {
       "name": "earth20",
      "author": "unsplash",
      "url": "https://raw.githubusercontent.com/edwinmacalopu/wxllpaper/master/wow21_green.png",
      "thumbnail": "https://raw.githubusercontent.com/edwinmacalopu/wxllpaper/master/wow21_green.png",
      "dimensions": "2500 x 3840",
      "copyright": "Free (do whatever you want)",
      "collections": "featured,earth"
    },
    {
       "name": "earth19",
      "author": "unsplash",
      "url": "https://raw.githubusercontent.com/edwinmacalopu/wxllpaper/master/wow21blur.png",
      "thumbnail": "https://raw.githubusercontent.com/edwinmacalopu/wxllpaper/master/wow21blur.png",
      "dimensions": "2500 x 3840",
      "copyright": "Free (do whatever you want)",
      "collections": "featured,earth"
    },
     {
       "name": "earth18",
      "author": "unsplash",
      "url": "https://raw.githubusercontent.com/edwinmacalopu/wxllpaper/master/wow21.png",
      "thumbnail": "https://raw.githubusercontent.com/edwinmacalopu/wxllpaper/master/wow21.png",
      "dimensions": "2500 x 3840",
      "copyright": "Free (do whatever you want)",
      "collections": "featured,earth"
    },
    {
       "name": "earth17",
      "author": "unsplash",
      "url": "https://raw.githubusercontent.com/edwinmacalopu/wxllpaper/master/acudff.png",
      "thumbnail": "https://raw.githubusercontent.com/edwinmacalopu/wxllpaper/master/acudff.png",
      "dimensions": "2500 x 3840",
      "copyright": "Free (do whatever you want)",
      "collections": "featured,earth"
    },
    {
       "name": "earth16",
      "author": "unsplash",
      "url": "https://raw.githubusercontent.com/edwinmacalopu/wxllpaper/master/acud.png",
      "thumbnail": "https://raw.githubusercontent.com/edwinmacalopu/wxllpaper/master/acud.png",
      "dimensions": "2500 x 3840",
      "copyright": "Free (do whatever you want)",
      "collections": "featured,earth"
    },
    {
       "name": "earth15",
      "author": "unsplash",
      "url": "https://raw.githubusercontent.com/edwinmacalopu/wxllpaper/master/puentes.png",
      "thumbnail": "https://raw.githubusercontent.com/edwinmacalopu/wxllpaper/master/puentes.png",
      "dimensions": "2500 x 3840",
      "copyright": "Free (do whatever you want)",
      "collections": "featured,earth"
    },
    {
       "name": "car white",
      "author": "unsplash",
      "url": "https://raw.githubusercontent.com/edwinmacalopu/wxllpaper/master/card6.png",
      "thumbnail": "https://raw.githubusercontent.com/edwinmacalopu/wxllpaper/master/card6.png",
      "dimensions": "2500 x 3840",
      "copyright": "Free (do whatever you want)",
      "collections": "featured,cars"
    },
    {
       "name": "car yellow3",
      "author": "unsplash",
      "url": "https://raw.githubusercontent.com/edwinmacalopu/wxllpaper/master/card5.png",
      "thumbnail": "https://raw.githubusercontent.com/edwinmacalopu/wxllpaper/master/card5.png",
      "dimensions": "2500 x 3840",
      "copyright": "Free (do whatever you want)",
      "collections": "featured,cars"
    },
    {
       "name": "car yellow2",
      "author": "unsplash",
      "url": "https://raw.githubusercontent.com/edwinmacalopu/wxllpaper/master/card3.png",
      "thumbnail": "https://raw.githubusercontent.com/edwinmacalopu/wxllpaper/master/card3.png",
      "dimensions": "1868 x 3840",
      "copyright": "Free (do whatever you want)",
      "collections": "featured,cars"
    },
    {
       "name": "car red2",
      "author": "unsplash",
      "url": "https://raw.githubusercontent.com/edwinmacalopu/wxllpaper/master/card2.png",
      "thumbnail": "https://raw.githubusercontent.com/edwinmacalopu/wxllpaper/master/card2.png",
      "dimensions": "1868 x 3840",
      "copyright": "Free (do whatever you want)",
      "collections": "featured,cars"
    },
    {
       "name": "car yellow",
      "author": "unsplash",
      "url": "https://raw.githubusercontent.com/edwinmacalopu/wxllpaper/master/card1.png",
      "thumbnail": "https://raw.githubusercontent.com/edwinmacalopu/wxllpaper/master/card1.png",
      "dimensions": "1868 x 3840",
      "copyright": "Free (do whatever you want)",
      "collections": "featured,cars"
    },
    {
       "name": "car red",
      "author": "unsplash",
      "url": "https://raw.githubusercontent.com/edwinmacalopu/wxllpaper/master/card.png",
      "thumbnail": "https://raw.githubusercontent.com/edwinmacalopu/wxllpaper/master/card.png",
      "dimensions": "1868 x 3840",
      "copyright": "Free (do whatever you want)",
      "collections": "featured,cars"
    },
    {
       "name": "earth14",
      "author": "unsplash",
      "url": "https://raw.githubusercontent.com/edwinmacalopu/wxllpaper/master/forest_gun.png",
      "thumbnail": "https://raw.githubusercontent.com/edwinmacalopu/wxllpaper/master/forest_gun.png",
      "dimensions": "1868 x 3840",
      "copyright": "Free (do whatever you want)",
      "collections": "featured,earth"
    },
     {
       "name": "liquid white",
      "author": "miluwalls",
      "url": "https://raw.githubusercontent.com/edwinmacalopu/wxllpaper/master/liquid_24.png",
      "thumbnail": "https://raw.githubusercontent.com/edwinmacalopu/wxllpaper/master/liquid_24_pre.png",
      "dimensions": "1868 x 3840",
      "copyright": "Free (do whatever you want)",
      "collections": "featured,abstract"
    },
    {
       "name": "liquid purple",
      "author": "miluwalls",
      "url": "https://raw.githubusercontent.com/edwinmacalopu/wxllpaper/master/liquid_23.png",
      "thumbnail": "https://raw.githubusercontent.com/edwinmacalopu/wxllpaper/master/liquid_23_pre.png",
      "dimensions": "1868 x 3840",
      "copyright": "Free (do whatever you want)",
      "collections": "featured,abstract"
    },
    {
       "name": "liquid red",
      "author": "miluwalls",
      "url": "https://raw.githubusercontent.com/edwinmacalopu/wxllpaper/master/liq_12.png",
      "thumbnail": "https://raw.githubusercontent.com/edwinmacalopu/wxllpaper/master/liq_12_pre.png",
      "dimensions": "1868 x 3840",
      "copyright": "Free (do whatever you want)",
      "collections": "featured,abstract"
    },
    {
       "name": "memphis09",
      "author": "miluwalls",
      "url": "https://raw.githubusercontent.com/edwinmacalopu/wxllpaper/master/mephi123.png",
      "thumbnail": "https://raw.githubusercontent.com/edwinmacalopu/wxllpaper/master/mephi123.png",
      "dimensions": "1868 x 3840",
      "copyright": "Free (do whatever you want)",
      "collections": "featured,memphis,earth"
    },
    {
       "name": "earth13",
      "author": "miluwalls",
      "url": "https://raw.githubusercontent.com/edwinmacalopu/wxllpaper/master/asteporir.png",
      "thumbnail": "https://raw.githubusercontent.com/edwinmacalopu/wxllpaper/master/asteporir.png",
      "dimensions": "1868 x 3840",
      "copyright": "Free (do whatever you want)",
      "collections": "featured,earth"
    },
    {
       "name": "earth12",
      "author": "unsplash",
      "url": "https://raw.githubusercontent.com/edwinmacalopu/wxllpaper/master/FOREST.png",
      "thumbnail": "https://raw.githubusercontent.com/edwinmacalopu/wxllpaper/master/FOREST.png",
      "dimensions": "1868 x 3840",
      "copyright": "Free (do whatever you want)",
      "collections": "featured,earth"
    },
    {
       "name": "Astronaut",
      "author": "miluwalls",
      "url": "https://raw.githubusercontent.com/edwinmacalopu/wxllpaper/master/ASTRONA.png",
      "thumbnail": "https://raw.githubusercontent.com/edwinmacalopu/wxllpaper/master/ASTRONA.png",
      "dimensions": "1868 x 3840",
      "copyright": "Free (do whatever you want)",
      "collections": "featured,abstract"
    },
    {
       "name": "earth11",
      "author": "unsplash",
      "url": "https://raw.githubusercontent.com/edwinmacalopu/wxllpaper/master/mountainssss.png",
      "thumbnail": "https://raw.githubusercontent.com/edwinmacalopu/wxllpaper/master/mountainssss.png",
      "dimensions": "1868 x 3840",
      "copyright": "Free (do whatever you want)",
      "collections": "featured,earth"
    },
     {
       "name": "earth10",
      "author": "unsplash",
      "url": "https://raw.githubusercontent.com/edwinmacalopu/wxllpaper/master/ocean.png",
      "thumbnail": "https://raw.githubusercontent.com/edwinmacalopu/wxllpaper/master/ocean.png",
      "dimensions": "1868 x 3840",
      "copyright": "Free (do whatever you want)",
      "collections": "featured,earth"
    },
    {
       "name": "earth09",
      "author": "unsplash",
      "url": "https://raw.githubusercontent.com/edwinmacalopu/wxllpaper/master/clielo.png",
      "thumbnail": "https://raw.githubusercontent.com/edwinmacalopu/wxllpaper/master/clielo.png",
      "dimensions": "1868 x 3840",
      "copyright": "Free (do whatever you want)",
      "collections": "featured,earth"
    },
    {
       "name": "architecture10",
      "author": "unsplash",
      "url": "https://raw.githubusercontent.com/edwinmacalopu/wxllpaper/master/madera.png",
      "thumbnail": "https://raw.githubusercontent.com/edwinmacalopu/wxllpaper/master/madera.png",
      "dimensions": "1868 x 3840",
      "copyright": "Free (do whatever you want)",
      "collections": "featured,architecture"
    },
    {
       "name": "earth08",
      "author": "unsplash",
      "url": "https://raw.githubusercontent.com/edwinmacalopu/wxllpaper/master/earth345.png",
      "thumbnail": "https://raw.githubusercontent.com/edwinmacalopu/wxllpaper/master/earth345.png",
      "dimensions": "1868 x 3840",
      "copyright": "Free (do whatever you want)",
      "collections": "featured,earth"
    },
    {
       "name": "architecture09",
      "author": "unsplash",
      "url": "https://raw.githubusercontent.com/edwinmacalopu/wxllpaper/master/archi7.png",
      "thumbnail": "https://raw.githubusercontent.com/edwinmacalopu/wxllpaper/master/archi7.png",
      "dimensions": "1868 x 3840",
      "copyright": "Free (do whatever you want)",
      "collections": "featured,architecture"
    },
    {
       "name": "architecture08",
      "author": "unsplash",
      "url": "https://raw.githubusercontent.com/edwinmacalopu/wxllpaper/master/archi36.png",
      "thumbnail": "https://raw.githubusercontent.com/edwinmacalopu/wxllpaper/master/archi36.png",
      "dimensions": "1868 x 3840",
      "copyright": "Free (do whatever you want)",
      "collections": "featured,architecture"
    },
    {
       "name": "architecture07",
      "author": "unsplash",
      "url": "https://raw.githubusercontent.com/edwinmacalopu/wxllpaper/master/archi35.png",
      "thumbnail": "https://raw.githubusercontent.com/edwinmacalopu/wxllpaper/master/archi35.png",
      "dimensions": "1868 x 3840",
      "copyright": "Free (do whatever you want)",
      "collections": "featured,architecture"
    },
    {
       "name": "architecture06",
      "author": "unsplash",
      "url": "https://raw.githubusercontent.com/edwinmacalopu/wxllpaper/master/archi34.png",
      "thumbnail": "https://raw.githubusercontent.com/edwinmacalopu/wxllpaper/master/archi34.png",
      "dimensions": "1868 x 3840",
      "copyright": "Free (do whatever you want)",
      "collections": "featured,architecture"
    },
    {
       "name": "earth07",
      "author": "unsplash",
      "url": "https://raw.githubusercontent.com/edwinmacalopu/wxllpaper/master/forest.png",
      "thumbnail": "https://raw.githubusercontent.com/edwinmacalopu/wxllpaper/master/forest.png",
      "dimensions": "1868 x 3840",
      "copyright": "Free (do whatever you want)",
      "collections": "featured,earth"
    },
     {
       "name": "earth06",
      "author": "unsplash",
      "url": "https://raw.githubusercontent.com/edwinmacalopu/wxllpaper/master/eartdddd.png",
      "thumbnail": "https://raw.githubusercontent.com/edwinmacalopu/wxllpaper/master/eartdddd.png",
      "dimensions": "1868 x 3840",
      "copyright": "Free (do whatever you want)",
      "collections": "featured,earth"
    },
     {
       "name": "memphis08",
      "author": "miluwalls",
      "url": "https://raw.githubusercontent.com/edwinmacalopu/wxllpaper/master/MINIT3.png",
      "thumbnail": "https://raw.githubusercontent.com/edwinmacalopu/wxllpaper/master/MINIT3.png",
      "dimensions": "1868 x 3840",
      "copyright": "Free (do whatever you want)",
      "collections": "featured,memphis"
    },
    {
       "name": "earth05",
      "author": "miluwalls",
      "url": "https://raw.githubusercontent.com/edwinmacalopu/wxllpaper/master/EATR5.png",
      "thumbnail": "https://raw.githubusercontent.com/edwinmacalopu/wxllpaper/master/EATR5.png",
      "dimensions": "1868 x 3840",
      "copyright": "Free (do whatever you want)",
      "collections": "featured,earth"
    },
    {
       "name": "architecture05",
      "author": "miluwalls",
      "url": "https://raw.githubusercontent.com/edwinmacalopu/wxllpaper/master/art12.png",
      "thumbnail": "https://raw.githubusercontent.com/edwinmacalopu/wxllpaper/master/art12.png",
      "dimensions": "1868 x 3840",
      "copyright": "Free (do whatever you want)",
      "collections": "featured,architecture"
    },
     {
       "name": "earth04",
      "author": "miluwalls",
      "url": "https://raw.githubusercontent.com/edwinmacalopu/wxllpaper/master/eart4.png",
      "thumbnail": "https://raw.githubusercontent.com/edwinmacalopu/wxllpaper/master/eart4.png",
      "dimensions": "1868 x 3840",
      "copyright": "Free (do whatever you want)",
      "collections": "featured,earth"
    },
    {
       "name": "earth03",
      "author": "miluwalls",
      "url": "https://raw.githubusercontent.com/edwinmacalopu/wxllpaper/master/eart3.png",
      "thumbnail": "https://raw.githubusercontent.com/edwinmacalopu/wxllpaper/master/eart3.png",
      "dimensions": "1868 x 3840",
      "copyright": "Free (do whatever you want)",
      "collections": "featured,earth"
    },
    {
       "name": "earth02",
      "author": "miluwalls",
      "url": "https://raw.githubusercontent.com/edwinmacalopu/wxllpaper/master/eart2.png",
      "thumbnail": "https://raw.githubusercontent.com/edwinmacalopu/wxllpaper/master/eart2.png",
      "dimensions": "1868 x 3840",
      "copyright": "Free (do whatever you want)",
      "collections": "featured,earth"
    },
    {
       "name": "earth01",
      "author": "miluwalls",
      "url": "https://raw.githubusercontent.com/edwinmacalopu/wxllpaper/master/eart1.png",
      "thumbnail": "https://raw.githubusercontent.com/edwinmacalopu/wxllpaper/master/eart1.png",
      "dimensions": "1868 x 3840",
      "copyright": "Free (do whatever you want)",
      "collections": "featured,earth"
    },
    {
       "name": "architecture04",
      "author": "miluwalls",
      "url": "https://raw.githubusercontent.com/edwinmacalopu/wxllpaper/master/is.png",
      "thumbnail": "https://raw.githubusercontent.com/edwinmacalopu/wxllpaper/master/is.png",
      "dimensions": "1868 x 3840",
      "copyright": "Free (do whatever you want)",
      "collections": "featured,architecture"
    },
    {
       "name": "architecture03",
      "author": "miluwalls",
      "url": "https://raw.githubusercontent.com/edwinmacalopu/wxllpaper/master/GOEDS.png",
      "thumbnail": "https://raw.githubusercontent.com/edwinmacalopu/wxllpaper/master/GOEDS.png",
      "dimensions": "1868 x 3840",
      "copyright": "Free (do whatever you want)",
      "collections": "featured,architecture"
    },
    {
       "name": "architecture02",
      "author": "miluwalls",
      "url": "https://raw.githubusercontent.com/edwinmacalopu/wxllpaper/master/OROJOED.png",
      "thumbnail": "https://raw.githubusercontent.com/edwinmacalopu/wxllpaper/master/OROJOED.png",
      "dimensions": "1868 x 3840",
      "copyright": "Free (do whatever you want)",
      "collections": "featured,architecture"
    },
    {
       "name": "architecture01",
      "author": "miluwalls",
      "url": "https://raw.githubusercontent.com/edwinmacalopu/wxllpaper/master/GORR.png",
      "thumbnail": "https://raw.githubusercontent.com/edwinmacalopu/wxllpaper/master/GORR.png",
      "dimensions": "1868 x 3840",
      "copyright": "Free (do whatever you want)",
      "collections": "featured,architecture"
    },
    {
       "name": "memphis07",
      "author": "miluwalls",
      "url": "https://raw.githubusercontent.com/edwinmacalopu/wxllpaper/master/finals59.png",
      "thumbnail": "https://raw.githubusercontent.com/edwinmacalopu/wxllpaper/master/finals59.png",
      "dimensions": "1868 x 3840",
      "copyright": "Free (do whatever you want)",
      "collections": "featured,memphis"
    },
    {
       "name": "memphis06",
      "author": "miluwalls",
      "url": "https://raw.githubusercontent.com/edwinmacalopu/wxllpaper/master/finals_good.png",
      "thumbnail": "https://raw.githubusercontent.com/edwinmacalopu/wxllpaper/master/finals_good.png",
      "dimensions": "1868 x 3840",
      "copyright": "Free (do whatever you want)",
      "collections": "featured,memphis"
    },
     {
       "name": "memphis05",
      "author": "miluwalls",
      "url": "https://raw.githubusercontent.com/edwinmacalopu/wxllpaper/master/GOOWHITE.png",
      "thumbnail": "https://raw.githubusercontent.com/edwinmacalopu/wxllpaper/master/GOOWHITE.png",
      "dimensions": "1868 x 3840",
      "copyright": "Free (do whatever you want)",
      "collections": "featured,memphis"
    },
    {
       "name": "memphis04",
      "author": "miluwalls",
      "url": "https://raw.githubusercontent.com/edwinmacalopu/wxllpaper/master/GOOFDD.png",
      "thumbnail": "https://raw.githubusercontent.com/edwinmacalopu/wxllpaper/master/GOOFDD.png",
      "dimensions": "1868 x 3840",
      "copyright": "Free (do whatever you want)",
      "collections": "featured,memphis"
    },
    {
       "name": "memphis03",
      "author": "miluwalls",
      "url": "https://raw.githubusercontent.com/edwinmacalopu/wxllpaper/master/goo_3.png",
      "thumbnail": "https://raw.githubusercontent.com/edwinmacalopu/wxllpaper/master/goo_3.png",
      "dimensions": "1868 x 3840",
      "copyright": "Free (do whatever you want)",
      "collections": "featured,memphis"
    },
    {
       "name": "memphis02",
      "author": "miluwalls",
      "url": "https://raw.githubusercontent.com/edwinmacalopu/wxllpaper/master/good.png",
      "thumbnail": "https://raw.githubusercontent.com/edwinmacalopu/wxllpaper/master/good.png",
      "dimensions": "1868 x 3840",
      "copyright": "Free (do whatever you want)",
      "collections": "featured,memphis"
    },
    {
       "name": "memphis01",
      "author": "miluwalls",
      "url": "https://raw.githubusercontent.com/edwinmacalopu/wxllpaper/master/blac_puro.png",
      "thumbnail": "https://raw.githubusercontent.com/edwinmacalopu/wxllpaper/master/blac_puro.png",
      "dimensions": "1868 x 3840",
      "copyright": "Free (do whatever you want)",
      "collections": "featured,memphis"
    },
    {
       "name": "memphis0",
      "author": "miluwalls",
      "url": "https://raw.githubusercontent.com/edwinmacalopu/wxllpaper/master/m_purbpl.png",
      "thumbnail": "https://raw.githubusercontent.com/edwinmacalopu/wxllpaper/master/m_purbpl.png",
      "dimensions": "1868 x 3840",
      "copyright": "Free (do whatever you want)",
      "collections": "featured,memphis"
    },
    {
       "name": "windmill",
      "author": "miluwalls",
      "url": "https://raw.githubusercontent.com/edwinmacalopu/wxllpaper/master/windmill.png",
      "thumbnail": "https://raw.githubusercontent.com/edwinmacalopu/wxllpaper/master/windmill.png",
      "dimensions": "1242 x 2208",
      "copyright": "Free (do whatever you want)",
      "collections": "featured,abstract"
    },
    {
       "name": "green asteri",
      "author": "miluwalls",
      "url": "https://raw.githubusercontent.com/edwinmacalopu/wxllpaper/master/green-a.png",
      "thumbnail": "https://raw.githubusercontent.com/edwinmacalopu/wxllpaper/master/green-a.png",
      "dimensions": "1242 x 2208",
      "copyright": "Free (do whatever you want)",
      "collections": "featured,abstract"
    },
     {
       "name": "red asteri",
      "author": "miluwalls",
      "url": "https://raw.githubusercontent.com/edwinmacalopu/wxllpaper/master/red_a.png",
      "thumbnail": "https://raw.githubusercontent.com/edwinmacalopu/wxllpaper/master/red_a.png",
      "dimensions": "1242 x 2208",
      "copyright": "Free (do whatever you want)",
      "collections": "featured,abstract"
    },
    {
       "name": "purple asteri",
      "author": "miluwalls",
      "url": "https://raw.githubusercontent.com/edwinmacalopu/wxllpaper/master/purple_a.png",
      "thumbnail": "https://raw.githubusercontent.com/edwinmacalopu/wxllpaper/master/purple_a.png",
      "dimensions": "1242 x 2208",
      "copyright": "Free (do whatever you want)",
      "collections": "featured,abstract"
    },
    {
       "name": "blue asteri",
      "author": "miluwalls",
      "url": "https://raw.githubusercontent.com/edwinmacalopu/wxllpaper/master/blue_a.png",
      "thumbnail": "https://raw.githubusercontent.com/edwinmacalopu/wxllpaper/master/blue_a.png",
      "dimensions": "1242 x 2208",
      "copyright": "Free (do whatever you want)",
      "collections": "featured,abstract"
    },
    {
       "name": "yellow asteri",
      "author": "miluwalls",
      "url": "https://raw.githubusercontent.com/edwinmacalopu/wxllpaper/master/hellow.png",
      "thumbnail": "https://raw.githubusercontent.com/edwinmacalopu/wxllpaper/master/hellow.png",
      "dimensions": "1242 x 2208",
      "copyright": "Free (do whatever you want)",
      "collections": "featured,abstract"
    },
     {
       "name": "blue blur",
      "author": "miluwalls",
      "url": "https://raw.githubusercontent.com/edwinmacalopu/wxllpaper/master/TRIANGLE_BLUE.png",
      "thumbnail": "https://raw.githubusercontent.com/edwinmacalopu/wxllpaper/master/TRIANGLE_BLUE.png",
      "dimensions": "1868 x 3840",
      "copyright": "Free (do whatever you want)",
      "collections": "featured,abstract"
    },
    {
       "name": "blue",
      "author": "miluwalls",
      "url": "https://raw.githubusercontent.com/edwinmacalopu/wxllpaper/master/TRIANGLE_BLUE_TRI.png",
      "thumbnail": "https://raw.githubusercontent.com/edwinmacalopu/wxllpaper/master/TRIANGLE_BLUE_TRI.png",
      "dimensions": "1868 x 3840",
      "copyright": "Free (do whatever you want)",
      "collections": "featured,abstract"
    },
     {
       "name": "green blur",
      "author": "miluwalls",
      "url": "https://raw.githubusercontent.com/edwinmacalopu/wxllpaper/master/green_blu.png",
      "thumbnail": "https://raw.githubusercontent.com/edwinmacalopu/wxllpaper/master/green_blu.png",
      "dimensions": "1868 x 3840",
      "copyright": "Free (do whatever you want)",
      "collections": "featured,abstract"
    },
    {
       "name": "green",
      "author": "miluwalls",
      "url": "https://raw.githubusercontent.com/edwinmacalopu/wxllpaper/master/green.png",
      "thumbnail": "https://raw.githubusercontent.com/edwinmacalopu/wxllpaper/master/green.png",
      "dimensions": "1868 x 3840",
      "copyright": "Free (do whatever you want)",
      "collections": "featured,abstract"
    },
    {
       "name": "red blur",
      "author": "miluwalls",
      "url": "https://raw.githubusercontent.com/edwinmacalopu/wxllpaper/master/red_blu.png",
      "thumbnail": "https://raw.githubusercontent.com/edwinmacalopu/wxllpaper/master/red_blu.png",
      "dimensions": "1868 x 3840",
      "copyright": "Free (do whatever you want)",
      "collections": "featured,abstract"
    },
    {
       "name": "red",
      "author": "miluwalls",
      "url": "https://raw.githubusercontent.com/edwinmacalopu/wxllpaper/master/red.png",
      "thumbnail": "https://raw.githubusercontent.com/edwinmacalopu/wxllpaper/master/red.png",
      "dimensions": "1868 x 3840",
      "copyright": "Free (do whatever you want)",
      "collections": "featured,abstract"
    },    
    {
      "name": "blue Shae",
      "author": "miluwalls",
      "url": "https://i.imgur.com/RpQtBnc.png",
      "thumbnail": "https://i.imgur.com/RpQtBnc.png",
      "dimensions": "1868 x 3840",
      "copyright": "Free (do whatever you want)",
      "collections": "featured,abstract"
      
    },
     {
      "name": "blue",
      "author": "miluwalls",
      "url": "https://i.imgur.com/jaQ0TXe.png",
      "thumbnail": "https://i.imgur.com/jaQ0TXe.png",
      "dimensions": "1242 x 2208",
      "copyright": "Free (do whatever you want)",
      "collections": "featured,abstract"
      
    }, 
     {
      "name": "blu",
      "author": "miluwalls",
      "url": "https://i.imgur.com/UXFhWAH.png",
      "thumbnail": "https://i.imgur.com/UXFhWAH.png",
      "dimensions": "1242 x 2208",
      "copyright": "Free (do whatever you want)",
      "collections": "featured,abstract"
    }, 
    
     {
      "name": "helow",
      "author": "miluwalls",
      "url": "https://i.imgur.com/5Rmrc2B.png",
      "thumbnail": "https://i.imgur.com/5Rmrc2B.png",
      "dimensions": "1242 x 2208",
      "copyright": "Free (do whatever you want)",
      "collections": "featured,abstract"
    }, 
    {
      "name": "Wallsplash 8",
      "author": "miluwalls",
      "url": "https://i.imgur.com/CVi5NIq.png",
      "thumbnail": "https://i.imgur.com/CVi5NIq.png",
      "dimensions": "1242 x 2208",
      "copyright": "Free (do whaktever you want)",
      "collections": "featured,abstract"
    }
  ]
}
