{
  "Collections": [
    {
      "name": "abstract",
      "preview_url": "https://i.imgur.com/UXFhWAH.png",
      "preview_thumbnail_url": "https://i.imgur.com/UXFhWAH.png"
    },
    {
      "name": "City",
      "preview_url": "https://github.com/jahirfiquitiva/Website-Resources/raw/master/wallpapers/unsplash_c.png",
      "preview_thumbnail_url": "https://github.com/jahirfiquitiva/Website-Resources/raw/master/wallpapers/thumbnails/unsplash_c.png"
    },
    {
      "name": "Food",
      "preview_url": "https://github.com/jahirfiquitiva/Website-Resources/raw/master/wallpapers/unsplash_b.png",
      "preview_thumbnail_url": "https://github.com/jahirfiquitiva/Website-Resources/raw/master/wallpapers/thumbnails/unsplash_b.png"
    },
    {
      "name": "People",
      "preview_url": "https://github.com/jahirfiquitiva/Website-Resources/raw/master/wallpapers/unsplash_d.png",
      "preview_thumbnail_url": "https://github.com/jahirfiquitiva/Website-Resources/raw/master/wallpapers/thumbnails/unsplash_d.png"
    }
  ],
  "Wallpapers": [
    {
      "name": "ShotA",
      "author": "Someone",
      "url": "https://raw.githubusercontent.com/jahirfiquitiva/MinDesigns-Wallpapers/master/Wallpapers/Free/walla.jpg",
      "collections": "featured,landscapes,people",
      "downloadable": false
    },    
    {
      "name": "blue Shae",
      "author": "miluwalls",
      "url": "https://i.imgur.com/RpQtBnc.png",
      "thumbnail": "https://i.imgur.com/RpQtBnc.png",
      "dimensions": "1242 x 2208",
      "copyright": "Free (do whatever you want)",
      "collections": "featured,abstract"
      
    },
     {
      "name": "blue",
      "author": "miluwalls",
      "url": "https://i.imgur.com/jaQ0TXe.png",
      "thumbnail": "https://i.imgur.com/jaQ0TXe.png",
      "dimensions": "1242 x 2208",
      "copyright": "Free (do whatever you want)",
      "collections": "featured,abstract"
      
    }, 
     {
      "name": "blu",
      "author": "miluwalls",
      "url": "https://i.imgur.com/UXFhWAH.png",
      "thumbnail": "https://i.imgur.com/UXFhWAH.png",
      "dimensions": "1242 x 2208",
      "copyright": "Free (do whatever you want)",
      "collections": "featured,abstract"
    }, 
    
     {
      "name": "helow",
      "author": "miluwalls",
      "url": "https://i.imgur.com/5Rmrc2B.png",
      "thumbnail": "https://i.imgur.com/5Rmrc2B.png",
      "dimensions": "1242 x 2208",
      "copyright": "Free (do whatever you want)",
      "collections": "featured,abstract"
    }, 
    {
      "name": "Wallsplash 8",
      "author": "miluwalls",
      "url": "https://i.imgur.com/CVi5NIq.png",
      "thumbnail": "https://i.imgur.com/CVi5NIq.png",
      "dimensions": "1242 x 2208",
      "copyright": "Free (do whaktever you want)",
      "collections": "featured,abstract"
    }
  ]
}
